proxiflow/__init__.py
proxiflow/__main__.py
proxiflow/cli.py
proxiflow/config/__init__.py
proxiflow/config/config.py
proxiflow/core/__init__.py
proxiflow/core/cleaner.py
proxiflow/core/core_utils.py
proxiflow/core/engineer.py
proxiflow/core/normalizer.py
proxiflow/utils/__init__.py
proxiflow/utils/data.py
proxiflow/utils/errors.py
proxiflow/utils/logger.py
proxiflow-0.1.7.dist-info/LICENSE
proxiflow-0.1.7.dist-info/WHEEL
proxiflow-0.1.7.dist-info/METADATA
proxiflow-0.1.7.dist-info/RECORD
