Metadata-Version: 2.1
Name: proxiflow
Version: 0.1.7
Summary: Data Preprocessing flow tool in python
License: MIT
Author: Martin Tomes
Author-email: tomesm@gmail.com
Requires-Python: >=3.10,<3.11
Classifier: Development Status :: 1 - Planning
Classifier: Environment :: Console
Classifier: Intended Audience :: Developers
Classifier: License :: OSI Approved :: MIT License
Classifier: Operating System :: POSIX :: Linux
Classifier: Programming Language :: Python
Classifier: Programming Language :: Python :: 3
Classifier: Programming Language :: Python :: 3.10
Classifier: Programming Language :: Python :: 3.10
Classifier: Programming Language :: Python :: Implementation :: CPython
Classifier: Topic :: Scientific/Engineering
Requires-Dist: click (>=8.1.3,<9.0.0)
Requires-Dist: numpy (>=1.24.2,<2.0.0)
Requires-Dist: polars (>=0.16.7,<0.17.0)
Requires-Dist: pyaml (>=21.10.1,<22.0.0)
Requires-Dist: scipy (>=1.10.1,<2.0.0)
Project-URL: Bug Tracker, https://github.com/tomesm/proxiflow/issues
Project-URL: Documentation, http://proxiflow.readthedocs.io
Project-URL: Repository, https://github.com/tomesm/proxiflow
